bangla_text_renderer/__init__.py
bangla_text_renderer/renderer.py
bangla_text_renderer-1.4.1.dist-info/licenses/LICENSE.txt
bangla_text_renderer-1.4.1.dist-info/METADATA
bangla_text_renderer-1.4.1.dist-info/WHEEL
bangla_text_renderer-1.4.1.dist-info/top_level.txt
bangla_text_renderer-1.4.1.dist-info/RECORD
