Metadata-Version: 2.4
Name: bangla-text-renderer
Version: 1.4.1
Summary: Perfect Bangla/Bengali text rendering on images/video with correct vowel positioning and joint letter
Home-page: https://github.com/Mahfazzalin/bangla-text-renderer
Author: Mahfazzalin Shawon Reza
Author-email: mahfazzalin1@gmail.com
Keywords: bangla bengali text rendering image video vowel positioning perfect joint letter unicode typography
Classifier: Development Status :: 5 - Production/Stable
Classifier: Intended Audience :: Developers
Classifier: Topic :: Multimedia :: Graphics
Classifier: Topic :: Text Processing :: Linguistic
Classifier: License :: OSI Approved :: MIT License
Classifier: Programming Language :: Python :: 3
Classifier: Programming Language :: Python :: 3.7
Classifier: Programming Language :: Python :: 3.8
Classifier: Programming Language :: Python :: 3.9
Classifier: Programming Language :: Python :: 3.10
Classifier: Programming Language :: Python :: 3.11
Classifier: Programming Language :: Python :: 3.12
Requires-Python: >=3.7
License-File: LICENSE.txt
Requires-Dist: Pillow>=8.0.0
Dynamic: author
Dynamic: author-email
Dynamic: classifier
Dynamic: description
Dynamic: description-content-type
Dynamic: home-page
Dynamic: keywords
Dynamic: license-file
Dynamic: requires-dist
Dynamic: requires-python
Dynamic: summary
